ncrystal_core-4.2.12.dist-info/RECORD
ncrystal_core-4.2.12.dist-info/WHEEL
ncrystal_core-4.2.12.dist-info/entry_points.txt
ncrystal_core-4.2.12.dist-info/METADATA
ncrystal_core-4.2.12.dist-info/licenses/LICENSE
_ncrystal_core/__init__.py
_ncrystal_core/info.py
_ncrystal_core/data/bin/ncrystal-config
_ncrystal_core/data/include/NCrystal/NCPluginBoilerplate.hh
_ncrystal_core/data/include/NCrystal/NCRNG.hh
_ncrystal_core/data/include/NCrystal/ncrystal.h
_ncrystal_core/data/include/NCrystal/ncapi.h
_ncrystal_core/data/include/NCrystal/NCrystal.hh
_ncrystal_core/data/include/NCrystal/misc/NCCompositionUtils.hh
_ncrystal_core/data/include/NCrystal/misc/NCMsgCtrl.hh
_ncrystal_core/data/include/NCrystal/dump/NCDump.hh
_ncrystal_core/data/include/NCrystal/core/NCDefs.hh
_ncrystal_core/data/include/NCrystal/core/NCTypes.hh
_ncrystal_core/data/include/NCrystal/core/NCVariant.hh
_ncrystal_core/data/include/NCrystal/core/NCException.hh
_ncrystal_core/data/include/NCrystal/core/NCFmt.hh
_ncrystal_core/data/include/NCrystal/core/NCImmutBuf.hh
_ncrystal_core/data/include/NCrystal/core/NCSmallVector.hh
_ncrystal_core/data/include/NCrystal/core/NCMem.hh
_ncrystal_core/data/include/NCrystal/cinterface/ncrystal.h
_ncrystal_core/data/include/NCrystal/plugins/NCPluginMgmt.hh
_ncrystal_core/data/include/NCrystal/internal/elincscatter/NCElIncScatter.hh
_ncrystal_core/data/include/NCrystal/internal/atomdb/NCAtomDBExtender.hh
_ncrystal_core/data/include/NCrystal/internal/atomdb/NCAtomDB.hh
_ncrystal_core/data/include/NCrystal/internal/sanshardsphere/NCSANSSphScat.hh
_ncrystal_core/data/include/NCrystal/internal/sab/NCSABSampler.hh
_ncrystal_core/data/include/NCrystal/internal/sab/NCSABIntegrator.hh
_ncrystal_core/data/include/NCrystal/internal/sab/NCSABExtender.hh
_ncrystal_core/data/include/NCrystal/internal/sab/NCSABEval.hh
_ncrystal_core/data/include/NCrystal/internal/sab/NCSABSamplerModels.hh
_ncrystal_core/data/include/NCrystal/internal/sab/NCScatKnlData.hh
_ncrystal_core/data/include/NCrystal/internal/sab/NCSABFactory.hh
_ncrystal_core/data/include/NCrystal/internal/sab/NCSABUtils.hh
_ncrystal_core/data/include/NCrystal/internal/sab/NCSABUCN.hh
