Metadata-Version: 2.1
Name: ncrystal-core
Version: 4.2.12
Summary: Library for thermal neutron transport in crystals and other materials.
Author: NCrystal developers (Thomas Kittelmann, Xiao Xiao Cai)
License: 
Classifier: Programming Language :: Python :: 3
Classifier: License :: OSI Approved :: Apache Software License
Project-URL: Homepage, https://mctools.github.io/ncrystal/
Project-URL: Bug Tracker, https://github.com/mctools/ncrystal/issues
Requires-Python: >=3.8
